cloud_tpu_client/__init__.py
cloud_tpu_client/client.py
cloud_tpu_client/version.py
cloud_tpu_client-0.10.dist-info/METADATA
cloud_tpu_client-0.10.dist-info/WHEEL
cloud_tpu_client-0.10.dist-info/top_level.txt
cloud_tpu_client-0.10.dist-info/RECORD
