Metadata-Version: 2.1
Name: cloud-tpu-client
Version: 0.10
Summary: Client for using Cloud TPUs
Home-page: https://cloud.google.com/tpu/
Author: Google Inc.
Author-email: packages@tensorflow.org
License: Apache 2.0
Keywords: tensorflow tpu
Platform: UNKNOWN
Classifier: Development Status :: 5 - Production/Stable
Classifier: Intended Audience :: Developers
Classifier: Intended Audience :: Education
Classifier: Intended Audience :: Science/Research
Classifier: License :: OSI Approved :: Apache Software License
Classifier: Programming Language :: Python :: 3
Classifier: Programming Language :: Python :: 3.4
Classifier: Programming Language :: Python :: 3.5
Classifier: Programming Language :: Python :: 3.6
Classifier: Topic :: Scientific/Engineering
Classifier: Topic :: Scientific/Engineering :: Mathematics
Classifier: Topic :: Scientific/Engineering :: Artificial Intelligence
Classifier: Topic :: Software Development
Classifier: Topic :: Software Development :: Libraries
Classifier: Topic :: Software Development :: Libraries :: Python Modules
Requires-Dist: google-api-python-client (==1.8.0)
Requires-Dist: oauth2client
